scripts.py
PyGeoModel/__init__.py
PyGeoModel/data/computeModel.json
PyGeoModel/data/modelContext.txt
ogmsServer2/__init__.py
ogmsServer2/base.py
ogmsServer2/constants.py
ogmsServer2/openModel.py
ogmsServer2/data/PGA.tif
ogmsServer2/data/baseclip.tif
ogmsServer2/data/intensity.tif
ogmsServer2/data/地震群发滑坡概率评估预警模型_67c32dc057e89375/LandSlide-outputIntensitypbtyTif.tif
ogmsServer2/data/地震群发滑坡概率评估预警模型_67c32dc057e89375/LandSlide-outputPGApbtyTif.tif
ogmsServer2/data/地震群发滑坡概率评估预警模型_7972c0716caa1213/LandSlide-outputIntensitypbtyTif.tif
ogmsServer2/data/地震群发滑坡概率评估预警模型_7972c0716caa1213/LandSlide-outputPGApbtyTif.tif
ogmsServer2/data/地震群发滑坡概率评估预警模型_a044c410df669372/LandSlide-outputIntensitypbtyTif.tif
ogmsServer2/data/地震群发滑坡概率评估预警模型_a044c410df669372/LandSlide-outputPGApbtyTif.tif
ogmsServer2/data/地震群发滑坡概率评估预警模型_b6ba56c07bf80c30/LandSlide-outputIntensitypbtyTif.tif
ogmsServer2/data/地震群发滑坡概率评估预警模型_b6ba56c07bf80c30/LandSlide-outputPGApbtyTif.tif
ogmsServer2/openUtils/__init__.py
ogmsServer2/openUtils/exceptions.py
ogmsServer2/openUtils/http_client.py
ogmsServer2/openUtils/mdlUtils.py
ogmsServer2/openUtils/parameterValidator.py
ogmsServer2/openUtils/stateManager.py
pygeomodel-1.0.4.dist-info/licenses/LICENSE
pygeomodel-1.0.4.dist-info/METADATA
pygeomodel-1.0.4.dist-info/WHEEL
pygeomodel-1.0.4.dist-info/top_level.txt
pygeomodel-1.0.4.dist-info/RECORD
